chemformula/__init__.py
chemformula/chemformula.py
chemformula/chemformula.pyi
chemformula/config.py
chemformula/config.pyi
chemformula/elements.py
chemformula/elements.pyi
chemformula/py.typed
chemformula-1.5.0.dist-info/METADATA
chemformula-1.5.0.dist-info/WHEEL
chemformula-1.5.0.dist-info/licenses/LICENSE
chemformula-1.5.0.dist-info/RECORD
