Metadata-Version: 2.4
Name: chemformula
Version: 1.5.0
Summary: ChemFormula is a Python class for working with chemical formulas. It allows parsing chemical formulas, generating formatted output strings and calculating formula weights.
Project-URL: Homepage, https://github.com/molshape/ChemFormula
Project-URL: Issues, https://github.com/molshape/ChemFormula/issues
Project-URL: Repository, https://github.com/molshape/ChemFormula.git
Author-email: Axel Müller <molshape@gmx.net>
Maintainer-email: Axel Müller <molshape@gmx.net>
License-Expression: MIT
License-File: LICENSE
Classifier: License :: OSI Approved :: MIT License
Classifier: Operating System :: OS Independent
Classifier: Programming Language :: Python :: 3.10
Classifier: Programming Language :: Python :: 3.11
Classifier: Programming Language :: Python :: 3.12
Classifier: Topic :: Scientific/Engineering :: Chemistry
Requires-Python: >=3.10
Requires-Dist: casregnum>=1.1.2
